{
  "users": [
    {
      "id": 1,
      "userName": "admin",
      "email": "admin@gmail.com",
      "password": "admin123"
    },
    {
      "id": 2,
      "userName": "admin1",
      "email": "admin1@gmail.com",
      "password": "admin123"
    },
    {
      "id": 3,
      "userName": "fdsdfsdf",
      "email": "sadsdfd@sdffundsf.com",
      "password": "sdfssfsdfd"
    }
  ],
  "cards": [
    {
      "id": 1,
      "name": "Asmoranomardicadaistinaculdacar",
      "image_uris": {
        "png": "https://cards.scryfall.io/normal/front/d/9/d99a9a7d-d9ca-4c11-80ab-e39d5943a315.jpg?1632831210"
      }
    },
    {
      "id": 2,
      "name": "Kraul Raider",
      "image_uris": {
        "png": "https://cards.scryfall.io/normal/front/1/3/133d9d56-d906-4252-9954-e34cc8564ced.jpg?1617894866"
      }
    },
    {
      "id": 3,
      "name": "Austere Command",
      "image_uris": {
        "png": "https://cards.scryfall.io/normal/front/c/f/cf1f630e-8b55-4f5a-a7f2-3161801de767.jpg?1698988082"
      }
    }
  ]
}